Metadata-Version: 2.4
Name: jcm
Version: 1.0.0
Summary: JAX-based General Circulation Model
Author-email: dwatsonparris@ucsd.edu
License: Apache
Keywords: climate,machine-learning
Classifier: Development Status :: 3 - Alpha
Classifier: Topic :: Scientific/Engineering
Classifier: Intended Audience :: Science/Research
Classifier: License :: OSI Approved :: Apache Software License
Requires-Python: >=3.11
License-File: LICENSE
Requires-Dist: dinosaur
Requires-Dist: flax
Requires-Dist: jax-datetime
Requires-Dist: tree-math
Requires-Dist: hydra-core
Requires-Dist: xarray[io,parallel]
Requires-Dist: pytest-cov
Requires-Dist: sphinx
Requires-Dist: furo
Dynamic: license-file
